thinelc.cp310-win_amd64.pdb
thinelc.cp310-win_amd64.pyd
thinelc/__init__.py
thinelc-0.0.0.dist-info/METADATA
thinelc-0.0.0.dist-info/WHEEL
thinelc-0.0.0.dist-info/top_level.txt
thinelc-0.0.0.dist-info/RECORD
