Metadata-Version: 2.1
Name: thinelc
Version: 0.0.0
Summary: A thin ELC Wrapper for Python
Home-page: https://github.com/BolunZhangzbl/thinelc
Author: Bolun Zhang
Author-email: bolun_zhangzbl@outlook.com
License: UNKNOWN
Platform: UNKNOWN
Requires-Dist: Cython
